CHANGELOG.txt
LICENSE.txt
MANIFEST.in
README.txt
ez_setup.py
setup.cfg
setup.py
URLConvert.egg-info/PKG-INFO
URLConvert.egg-info/SOURCES.txt
URLConvert.egg-info/dependency_links.txt
URLConvert.egg-info/entry_points.txt
URLConvert.egg-info/not-zip-safe
URLConvert.egg-info/requires.txt
URLConvert.egg-info/top_level.txt
doc/Makefile
doc/index.txt
doc/source/api.rst
doc/source/conf.py
doc/source/index.rst
doc/source/manual.rst
doc/source/tech.rst
test/code.py
test/doc.py
urlconvert/__init__.py