Metadata-Version: 1.0
Name: URLConvert
Version: 0.3.2
Summary: A simple, extensible URL dispatcher
Home-page: http://jimmyg.org/work/code/urlconvert/index.html
Author: James Gardner
Author-email: UNKNOWN
License: GNU AGPLv3
Platform: UNKNOWN
Classifier: Development Status :: 3 - Alpha
Classifier: Environment :: Web Environment
Classifier: License :: OSI Approved :: GNU Affero General Public License v3
Classifier: Programming Language :: Python
